<?xml version="1.0" encoding="utf-8"?>
<ModMetaData>
  <name>Can't You See I'm Busy</name>
  <author>sum117</author>
  <packageId>sum117.cantyouseeimbusy</packageId>
  <supportedVersions>
    <li>1.6</li>
  </supportedVersions>
  <modVersion>1.0.5</modVersion>
  <description>
    When a raid hits and your colonists are drafted, Can't You See I'm Busy freezes need decay and blocks mental breaks, so they fight instead of wandering off for a snack. Needs resume exactly where they left off when combat ends.
  </description>
  <modDependencies>
		<li>
			<packageId>brrainz.harmony</packageId>
			<displayName>Harmony</displayName>
			<downloadUrl>https://github.com/pardeike/HarmonyRimWorld/releases/latest</downloadUrl>
			<steamWorkshopUrl>https://steamcommunity.com/workshop/filedetails/?id=2009463077</steamWorkshopUrl>
		</li>
  </modDependencies>
  <loadAfter>
    <li>brrainz.harmony</li>
  </loadAfter>
</ModMetaData>
